Workbook

Sheet Cómo usar
A1: Relevamiento de gestiones – Atención al Cliente
A2: Objetivo | B2: Revisar con Ventas, Call Center y Mesa de Informes todo lo que se puede gestionar, sumar información nueva y unificar criterios. Solo información, sin el paso a paso del sistema.
A3: Fuentes | B3: PG 02 Trámites de atención al cliente; IO 02.01 Servicios de energía; IO 02.02 Servicios de agua; IO 02.03 Servicios de TIC.
A4: Hojas | B4: Una hoja por servicio (Energía, Agua, TIC, Movilcoop, Otros servicios, General y administrativo) + Criterios comunes + Pendientes y contradicciones + Resumen.
A5: Qué completar | B5: Solo las celdas en amarillo: columnas de validación de cada sector (lista desplegable), Observaciones / info nueva, y las filas amarillas vacías al final de cada hoja para agregar gestiones que falten (ponerles un ID, por ej. E15, para que cuenten en el Resumen).
A6: Estados de validación | B6: Vigente = así se hace hoy · Se hace distinto = anotar cómo en Observaciones · No lo sabíamos = el sector no tenía esta info · No aplica = el sector no la gestiona · A definir = hay que decidir el criterio.
A7: Ejemplo de fila completada | B7: E10 Baja voluntaria → Validación Ventas: Vigente · Validación Call Center: No lo sabíamos · Validación Mesa de Informes: No aplica · Observaciones: 'Call Center informaba que podía pedirla cualquier familiar; unificar: solo titular o con autorización.'
A8: Pendientes y contradicciones | B8: Lista de huecos y diferencias detectadas en los documentos. Completar Quién define, Estado (Abierto / En revisión / Resuelto) y Resolución.
A9: Siguiente paso | B9: Con todo validado, se arma la guía de consulta rápida para los tres sectores.
A11: Celda para completar

Sheet Resumen
A1: Avance de la revisión por sector
A2: Se actualiza solo a medida que cada sector completa sus columnas de validación.
A4: Sector: Ventas
A5: Servicio | B5: Gestiones | C5: Vigente | D5: Se hace distinto | E5: No lo sabíamos | F5: No aplica | G5: A definir | H5: Sin revisar
A6: Energía | B6: =COUNTA('Energía'!$A$2:$A$25) | C6: =COUNTIF('Energía'!$I$2:$I$25,"Vigente") | D6: =COUNTIF('Energía'!$I$2:$I$25,"Se hace distinto") | E6: =COUNTIF('Energía'!$I$2:$I$25,"No lo sabíamos") | F6: =COUNTIF('Energía'!$I$2:$I$25,"No aplica") | G6: =COUNTIF('Energía'!$I$2:$I$25,"A definir") | H6: =B6-SUM(C6:G6)
A7: Agua | B7: =COUNTA('Agua'!$A$2:$A$19) | C7: =COUNTIF('Agua'!$I$2:$I$19,"Vigente") | D7: =COUNTIF('Agua'!$I$2:$I$19,"Se hace distinto") | E7: =COUNTIF('Agua'!$I$2:$I$19,"No lo sabíamos") | F7: =COUNTIF('Agua'!$I$2:$I$19,"No aplica") | G7: =COUNTIF('Agua'!$I$2:$I$19,"A definir") | H7: =B7-SUM(C7:G7)
A8: TIC | B8: =COUNTA('TIC'!$A$2:$A$22) | C8: =COUNTIF('TIC'!$I$2:$I$22,"Vigente") | D8: =COUNTIF('TIC'!$I$2:$I$22,"Se hace distinto") | E8: =COUNTIF('TIC'!$I$2:$I$22,"No lo sabíamos") | F8: =COUNTIF('TIC'!$I$2:$I$22,"No aplica") | G8: =COUNTIF('TIC'!$I$2:$I$22,"A definir") | H8: =B8-SUM(C8:G8)
A9: Movilcoop | B9: =COUNTA('Movilcoop'!$A$2:$A$19) | C9: =COUNTIF('Movilcoop'!$I$2:$I$19,"Vigente") | D9: =COUNTIF('Movilcoop'!$I$2:$I$19,"Se hace distinto") | E9: =COUNTIF('Movilcoop'!$I$2:$I$19,"No lo sabíamos") | F9: =COUNTIF('Movilcoop'!$I$2:$I$19,"No aplica") | G9: =COUNTIF('Movilcoop'!$I$2:$I$19,"A definir") | H9: =B9-SUM(C9:G9)
A10: Otros servicios | B10: =COUNTA('Otros servicios'!$A$2:$A$21) | C10: =COUNTIF('Otros servicios'!$I$2:$I$21,"Vigente") | D10: =COUNTIF('Otros servicios'!$I$2:$I$21,"Se hace distinto") | E10: =COUNTIF('Otros servicios'!$I$2:$I$21,"No lo sabíamos") | F10: =COUNTIF('Otros servicios'!$I$2:$I$21,"No aplica") | G10: =COUNTIF('Otros servicios'!$I$2:$I$21,"A definir") | H10: =B10-SUM(C10:G10)
A11: General y administrativo | B11: =COUNTA('General y administrativo'!$A$2:$A$17) | C11: =COUNTIF('General y administrativo'!$I$2:$I$17,"Vigente") | D11: =COUNTIF('General y administrativo'!$I$2:$I$17,"Se hace distinto") | E11: =COUNTIF('General y administrativo'!$I$2:$I$17,"No lo sabíamos") | F11: =COUNTIF('General y administrativo'!$I$2:$I$17,"No aplica") | G11: =COUNTIF('General y administrativo'!$I$2:$I$17,"A definir") | H11: =B11-SUM(C11:G11)
A12: Total | B12: =SUM(B6:B11) | C12: =SUM(C6:C11) | D12: =SUM(D6:D11) | E12: =SUM(E6:E11) | F12: =SUM(F6:F11) | G12: =SUM(G6:G11) | H12: =SUM(H6:H11)
A14: Sector: Call Center
A15: Servicio | B15: Gestiones | C15: Vigente | D15: Se hace distinto | E15: No lo sabíamos | F15: No aplica | G15: A definir | H15: Sin revisar
A16: Energía | B16: =COUNTA('Energía'!$A$2:$A$25) | C16: =COUNTIF('Energía'!$J$2:$J$25,"Vigente") | D16: =COUNTIF('Energía'!$J$2:$J$25,"Se hace distinto") | E16: =COUNTIF('Energía'!$J$2:$J$25,"No lo sabíamos") | F16: =COUNTIF('Energía'!$J$2:$J$25,"No aplica") | G16: =COUNTIF('Energía'!$J$2:$J$25,"A definir") | H16: =B16-SUM(C16:G16)
A17: Agua | B17: =COUNTA('Agua'!$A$2:$A$19) | C17: =COUNTIF('Agua'!$J$2:$J$19,"Vigente") | D17: =COUNTIF('Agua'!$J$2:$J$19,"Se hace distinto") | E17: =COUNTIF('Agua'!$J$2:$J$19,"No lo sabíamos") | F17: =COUNTIF('Agua'!$J$2:$J$19,"No aplica") | G17: =COUNTIF('Agua'!$J$2:$J$19,"A definir") | H17: =B17-SUM(C17:G17)
A18: TIC | B18: =COUNTA('TIC'!$A$2:$A$22) | C18: =COUNTIF('TIC'!$J$2:$J$22,"Vigente") | D18: =COUNTIF('TIC'!$J$2:$J$22,"Se hace distinto") | E18: =COUNTIF('TIC'!$J$2:$J$22,"No lo sabíamos") | F18: =COUNTIF('TIC'!$J$2:$J$22,"No aplica") | G18: =COUNTIF('TIC'!$J$2:$J$22,"A definir") | H18: =B18-SUM(C18:G18)
A19: Movilcoop | B19: =COUNTA('Movilcoop'!$A$2:$A$19) | C19: =COUNTIF('Movilcoop'!$J$2:$J$19,"Vigente") | D19: =COUNTIF('Movilcoop'!$J$2:$J$19,"Se hace distinto") | E19: =COUNTIF('Movilcoop'!$J$2:$J$19,"No lo sabíamos") | F19: =COUNTIF('Movilcoop'!$J$2:$J$19,"No aplica") | G19: =COUNTIF('Movilcoop'!$J$2:$J$19,"A definir") | H19: =B19-SUM(C19:G19)
A20: Otros servicios | B20: =COUNTA('Otros servicios'!$A$2:$A$21) | C20: =COUNTIF('Otros servicios'!$J$2:$J$21,"Vigente") | D20: =COUNTIF('Otros servicios'!$J$2:$J$21,"Se hace distinto") | E20: =COUNTIF('Otros servicios'!$J$2:$J$21,"No lo sabíamos") | F20: =COUNTIF('Otros servicios'!$J$2:$J$21,"No aplica") | G20: =COUNTIF('Otros servicios'!$J$2:$J$21,"A definir") | H20: =B20-SUM(C20:G20)
A21: General y administrativo | B21: =COUNTA('General y administrativo'!$A$2:$A$17) | C21: =COUNTIF('General y administrativo'!$J$2:$J$17,"Vigente") | D21: =COUNTIF('General y administrativo'!$J$2:$J$17,"Se hace distinto") | E21: =COUNTIF('General y administrativo'!$J$2:$J$17,"No lo sabíamos") | F21: =COUNTIF('General y administrativo'!$J$2:$J$17,"No aplica") | G21: =COUNTIF('General y administrativo'!$J$2:$J$17,"A definir") | H21: =B21-SUM(C21:G21)
A22: Total | B22: =SUM(B16:B21) | C22: =SUM(C16:C21) | D22: =SUM(D16:D21) | E22: =SUM(E16:E21) | F22: =SUM(F16:F21) | G22: =SUM(G16:G21) | H22: =SUM(H16:H21)
A24: Sector: Mesa de Informes
A25: Servicio | B25: Gestiones | C25: Vigente | D25: Se hace distinto | E25: No lo sabíamos | F25: No aplica | G25: A definir | H25: Sin revisar
A26: Energía | B26: =COUNTA('Energía'!$A$2:$A$25) | C26: =COUNTIF('Energía'!$K$2:$K$25,"Vigente") | D26: =COUNTIF('Energía'!$K$2:$K$25,"Se hace distinto") | E26: =COUNTIF('Energía'!$K$2:$K$25,"No lo sabíamos") | F26: =COUNTIF('Energía'!$K$2:$K$25,"No aplica") | G26: =COUNTIF('Energía'!$K$2:$K$25,"A definir") | H26: =B26-SUM(C26:G26)
A27: Agua | B27: =COUNTA('Agua'!$A$2:$A$19) | C27: =COUNTIF('Agua'!$K$2:$K$19,"Vigente") | D27: =COUNTIF('Agua'!$K$2:$K$19,"Se hace distinto") | E27: =COUNTIF('Agua'!$K$2:$K$19,"No lo sabíamos") | F27: =COUNTIF('Agua'!$K$2:$K$19,"No aplica") | G27: =COUNTIF('Agua'!$K$2:$K$19,"A definir") | H27: =B27-SUM(C27:G27)
A28: TIC | B28: =COUNTA('TIC'!$A$2:$A$22) | C28: =COUNTIF('TIC'!$K$2:$K$22,"Vigente") | D28: =COUNTIF('TIC'!$K$2:$K$22,"Se hace distinto") | E28: =COUNTIF('TIC'!$K$2:$K$22,"No lo sabíamos") | F28: =COUNTIF('TIC'!$K$2:$K$22,"No aplica") | G28: =COUNTIF('TIC'!$K$2:$K$22,"A definir") | H28: =B28-SUM(C28:G28)
A29: Movilcoop | B29: =COUNTA('Movilcoop'!$A$2:$A$19) | C29: =COUNTIF('Movilcoop'!$K$2:$K$19,"Vigente") | D29: =COUNTIF('Movilcoop'!$K$2:$K$19,"Se hace distinto") | E29: =COUNTIF('Movilcoop'!$K$2:$K$19,"No lo sabíamos") | F29: =COUNTIF('Movilcoop'!$K$2:$K$19,"No aplica") | G29: =COUNTIF('Movilcoop'!$K$2:$K$19,"A definir") | H29: =B29-SUM(C29:G29)
A30: Otros servicios | B30: =COUNTA('Otros servicios'!$A$2:$A$21) | C30: =COUNTIF('Otros servicios'!$K$2:$K$21,"Vigente") | D30: =COUNTIF('Otros servicios'!$K$2:$K$21,"Se hace distinto") | E30: =COUNTIF('Otros servicios'!$K$2:$K$21,"No lo sabíamos") | F30: =COUNTIF('Otros servicios'!$K$2:$K$21,"No aplica") | G30: =COUNTIF('Otros servicios'!$K$2:$K$21,"A definir") | H30: =B30-SUM(C30:G30)
A31: General y administrativo | B31: =COUNTA('General y administrativo'!$A$2:$A$17) | C31: =COUNTIF('General y administrativo'!$K$2:$K$17,"Vigente") | D31: =COUNTIF('General y administrativo'!$K$2:$K$17,"Se hace distinto") | E31: =COUNTIF('General y administrativo'!$K$2:$K$17,"No lo sabíamos") | F31: =COUNTIF('General y administrativo'!$K$2:$K$17,"No aplica") | G31: =COUNTIF('General y administrativo'!$K$2:$K$17,"A definir") | H31: =B31-SUM(C31:G31)
A32: Total | B32: =SUM(B26:B31) | C32: =SUM(C26:C31) | D32: =SUM(D26:D31) | E32: =SUM(E26:E31) | F32: =SUM(F26:F31) | G32: =SUM(G26:G31) | H32: =SUM(H26:H31)
A34: Pendientes abiertos | B34: =COUNTIF('Pendientes y contradicciones'!$H$2:$H$44,"Abierto")
A35: Pendientes resueltos | B35: =COUNTIF('Pendientes y contradicciones'!$H$2:$H$44,"Resuelto")

Sheet Energía
A1: ID | B1: Gestión | C1: Quién puede pedirla / condiciones | D1: Documentación | E1: Costo / qué se cobra | F1: Canales | G1: Intervienen / a quién se deriva | H1: Fuente | I1: Validación Ventas | J1: Validación Call Center | K1: Validación Mesa de Informes | L1: Observaciones / info nueva
A2: E01 | B2: Conexión monofásica – propietario | C2: Cualquier persona (socio o no). Si es a estrenar, ver E05. | D2: DNI/CUIT/CUIL; escritura o boleto de compraventa; certificado de instalación eléctrica apta (usuario y punto de medición); contrato social si es sociedad; foto del monolito listo (Anexo III); impuesto provincial de Rentas; inscripción en ARCA e Ingresos Brutos. | E2: Costo de conexión + suscripción de acciones. Sin garantía. | F2: Presencial / Web | G2: Oficina Técnica (factibilidad); Técnico de Servicios (conexión) | H2: IO 02.01 §5.1.1 / Fig. 1
A3: E02 | B3: Conexión monofásica – inquilino | C3: Inquilino con garante o depósito en garantía. | D3: DNI/CUIT/CUIL del inquilino, del propietario y del garante; contrato de alquiler con firmas certificadas (juez de paz o escribano); certificado apto (usuario y punto de medición); contrato social si es sociedad; foto impresa y firmada por el propietario del domicilio y monolito; monolito listo; Rentas; ARCA e IIBB. | E3: Costo de conexión + acciones + depósito en garantía (4 cuotas, 1ª de contado) si no hay garante. El depósito se devuelve en la baja. | F3: Presencial / Web | G3: Garante: socio de la Cooperativa y propietario | H3: IO 02.01 §5.1.1 / Fig. 1
A4: E03 | B4: Conexión trifásica – propietario | C4: Igual que monofásica + declaración de potencia. | D4: Igual que E01 + foto impresa y firmada por el propietario del domicilio y monolito + declaración jurada de potencia instalada (RPG/RIO 02.01). ARCA e IIBB en caso de comercio. | E4: Costo de conexión + suscripción de acciones. | F4: Presencial / Web | G4: Oficina Técnica; Técnico de Servicios | H4: IO 02.01 §5.1.1 / Fig. 2
A5: E04 | B5: Conexión trifásica – inquilino | C5: Inquilino con garante o depósito. | D5: Igual que E02 + declaración de potencia. (La figura menciona también 'Escritura copia'). | E5: Costo de conexión + acciones + depósito si no hay garante. | F5: Presencial / Web | G5: Garante: socio y propietario | H5: IO 02.01 §5.1.1 / Fig. 2
A6: E05 | B6: Conexión en lugar a estrenar | C6: Requiere factibilidad técnica afirmativa. | D6: Autorización municipal. | E6: — | F6: Presencial | G6: Oficina Técnica: si la factibilidad es negativa, el cliente habla con ellos. | H6: IO 02.01 §5.1.1
A7: E06 | B7: Certificado de instalación eléctrica apta | C7: Obligatorio en conexión nueva, reconexión con medidor retirado y cambio de categoría con cambio de instalación (Ley 10.281, ERSeP). | D7: 2 certificados: instalación del usuario y punto de medición. Por triplicado, firmado por propietario y electricista matriculado. Vivienda: electricista cat. III; tablero múltiple: cat. I o II. | E7: Vigencia: casa 5 años; comercio 3; pública concurrencia/cartelería/alumbrado/señalización 2; obra 1. | F7: — | G7: ERSeP (verificar matrícula) | H7: IO 02.01 §5.1.1
A8: E07 | B8: Pilares / monolito | C8: Según potencia y tipo. | D8: Anexo III: pilares mono y trifásicos hasta 5 kVA y mayores. Subterráneos, agrupaciones de medidores y transitorios de obra: consultar. | E8: — | F8: — | G8: Oficina Técnica | H8: IO 02.01 §5.1.1
A9: E08 | B9: Reconexión | C9: Con deuda paga. Corte > 30 días: titular o autorización del titular. | D9: Si el medidor fue retirado: certificado apto + inspección. Firma declaración jurada. | E9: Se cobra reconexión. | F9: Presencial / Caja (pedidos por WhatsApp 'Teletrabajo') | G9: Facturación (deuda); Técnico de Servicios | H9: IO 02.01 §5.1.2
A10: E09 | B10: Cambio de titularidad / razón social | C10: Entre inquilinos, inquilino↔propietario o por fallecimiento. Vienen ambas partes. | D10: Toma de lectura 2-3 días antes. Garante o depósito del nuevo titular. Certificado apto si corresponde (inspección de monolito). | E10: Cambio de nombre + suscripción de acciones. Al saliente se le hace nota de crédito por su depósito. | F10: Presencial | G10: Facturación (lectura); Banco de Sangre si hay adherentes; Servicios sociales (se transfieren o se dan de baja) | H10: IO 02.01 §5.1.3
A11: E10 | B11: Baja voluntaria | C11: La pide el titular. | D11: — | E11: Se factura consumo hasta la toma de lectura; se reintegra depósito si lo hubo. | F11: Presencial | G11: Facturación | H11: IO 02.01 §5.1.4
A12: E11 | B12: Traslado | C12: Sin deuda y con disponibilidad técnica en el nuevo domicilio. | D12: Inquilino: contrato con firmas certificadas + renovación de garantía. Propietario: escritura. | E12: Se cobra traslado. | F12: Presencial | G12: Oficina Técnica; Técnico de Servicios | H12: IO 02.01 §5.1.5
A13: E12 | B13: Facturación de obras | C13: La pide Oficina Técnica por mail (obras@). | D13: Cuenta de 'ventas a terceros' con el mismo mail que el convenio. | E13: Ventas factura y arma el plan de pago; el comitente firma el convenio (lo completa Contaduría). | F13: Mail interno | G13: Oficina Técnica; Contaduría | H13: IO 02.01 §5.1.6
A14: E13 | B14: Financiaciones (titular o garante) | C14: SIN DESARROLLAR en el instructivo. | G14: Gerencia Administrativa (aprobación) | H14: IO 02.01 §5.1.7
A15: E14 | B15: Prórrogas | C15: SIN DESARROLLAR en el instructivo. | H15: IO 02.01 §5.1.8

Sheet Agua
A1: ID | B1: Gestión | C1: Quién puede pedirla / condiciones | D1: Documentación | E1: Costo / qué se cobra | F1: Canales | G1: Intervienen / a quién se deriva | H1: Fuente | I1: Validación Ventas | J1: Validación Call Center | K1: Validación Mesa de Informes | L1: Observaciones / info nueva
A2: A01 | B2: Conexión urbana o rural – propietario | C2: Propietario. | D2: DNI; autorización municipal o final de obra; escritura o boleto; monolito listo; impuesto provincial de Rentas. | E2: Tarifa urbana 'Con medidor T1' o 'Rural T1'. Firma DJ, domicilio electrónico y financiación. | F2: Presencial / Web | G2: Oficina Técnica | H2: IO 02.02 §5.1-5.2 / Fig. 1
A3: A02 | B3: Conexión – inquilino | C3: A CONFIRMAR: el texto dice garante si es inquilino, pero también que el servicio está siempre a nombre del propietario. | D3: — | E3: — | F3: — | H3: IO 02.02 §5.2
A4: A03 | B4: Conexión en lugar a estrenar | C4: Factibilidad afirmativa con el permiso municipal. | D4: Permiso municipal. | E4: Si es negativa, Oficina Técnica informa el costo de la obra. | F4: Presencial | G4: Oficina Técnica | H4: IO 02.02 §5.2
A5: A04 | B5: Corte (colocación de cepo) | C5: Por falta de pago. | D5: — | E5: — | F5: — | G5: Lo genera Facturación | H5: IO 02.02 §5.2.2
A6: A05 | B6: Reconexión (quita de cepo) | C6: SIN DESARROLLAR. | F6: Presencial / Web | H6: IO 02.02 §5.2.3
A7: A06 | B7: Cambio de titularidad | C7: Solo por fallecimiento del titular o compra de la propiedad (el servicio va a nombre del propietario). | D7: Similar a energía. | E7: Suscripción de acciones si corresponde. | F7: Presencial | H7: IO 02.02 §5.2.5
A8: A07 | B8: Baja voluntaria | C8: La pide el titular. | D8: Declaración jurada de que la vivienda está libre de ocupantes. | E8: — | F8: Presencial | H8: IO 02.02 §5.2.6
A9: A08 | B9: Facturación de obras de agua | C9: La pide Oficina Técnica por mail. | D9: Igual que E12. | E9: Igual que E12. | F9: Mail interno | G9: Oficina Técnica; Contaduría | H9: IO 02.02 §5.2.7

Sheet TIC
A1: ID | B1: Gestión | C1: Quién puede pedirla / condiciones | D1: Documentación | E1: Costo / qué se cobra | F1: Canales | G1: Intervienen / a quién se deriva | H1: Fuente | I1: Validación Ventas | J1: Validación Call Center | K1: Validación Mesa de Informes | L1: Observaciones / info nueva
A2: T01 | B2: Teléfono – conexión | C2: Titular de energía en el domicilio / propietario / inquilino. | D2: Titular de energía: solo DNI. Propietario sin energía a su nombre: DNI + escritura. Inquilino: DNI + contrato con firmas certificadas + garante (cualquier asociado titular de energía). | E2: Depósito en garantía si corresponde. Tarifa residencial o comercial. Opciones: cobre o fibra, figura en guía, aparato común o especial. | F2: Presencial / Web / Teléfono | G2: Número según localidad (libro CNC) | H2: IO 02.03 §5.1.1
A3: T02 | B3: Internet por fibra óptica – conexión | C3: Mismos requisitos que teléfono. Si no tiene energía a su nombre, debe conectar teléfono antes (para ser asociado). | D3: Igual que T01. | E3: Inscripción $0. Conexión financiada en 4 cuotas sin interés. | F3: Presencial / Web / Teléfono | H3: IO 02.03 §5.2.1
A4: T03 | B4: Internet inalámbrico – conexión | C4: Puede no ser socio. Requiere verificación geográfica de recepción. | D4: Garante o 2 meses de abono por adelantado. | E4: Equipo vendido por la Cooperativa: contado o hasta 6 cuotas. | F4: Presencial | G4: Encargado de internet inalámbrico; Depósito (factura equipo) | H4: IO 02.03 §5.2.2
A5: T04 | B5: Televisión (IPTV) – conexión | C5: Ser socio (energía, agua o teléfono a su nombre) y tener internet. Si solo quiere TV: prestación de internet 'solo IPTV' sin abono. | D5: Garantía: la misma cargada en internet. | E5: Sin costo de conexión si adhiere a pago directo en ese momento. | F5: Presencial / Web / Teléfono | H5: IO 02.03 §5.3.1
A6: T05 | B6: TV – decodificadores adicionales (2 o 3 TV) | C6: Cliente con IPTV. | D6: — | E6: Se facturan y financian los decodificadores. | F6: Presencial | G6: Depósito (factura); Facturación (financia) | H6: IO 02.03 §5.3.1
A7: T06 | B7: Corte por falta de pago | C7: — | D7: — | E7: — | F7: — | G7: Lo genera Facturación | H7: IO 02.03 §5.2.3 / §5.3.4
A8: T07 | B8: Reconexión (teléfono, internet, TV) | C8: Con deuda paga. Corte > 30 días: titular o autorización. | D8: Firma declaración jurada. | E8: Se cobra reconexión. | F8: Presencial / Web / Caja automática | G8: Caja | H8: IO 02.03 §5.1.3 / §5.2.4 / §5.3.5
A9: T08 | B9: Cambio de titularidad | C9: Poco frecuente: cambio de inquilino, fallecimiento o necesidad del cliente. | D9: Similar a energía. | E9: — | F9: Presencial | G9: Definir guía, velocidad e cantidad de TV del nuevo titular | H9: IO 02.03 §5.1.4
A10: T09 | B10: Baja voluntaria | C10: La pide el titular. Devuelve equipos en comodato (ONT, decodificador, HDMI, control remoto, transformadores). | D10: — | E10: Se facturan los faltantes (ONT, STB, control, HDMI) y el saldo hasta el día de la baja. | F10: Presencial | G10: Depósito (remito de devolución); Facturación | H10: IO 02.03 §5.1.2
A11: T10 | B11: Traslado (teléfono, internet, TV) | C11: Sin deuda y con disponibilidad técnica. | D11: Inquilino: contrato con firmas certificadas + renovación de garantía. Propietario: escritura. | E11: Se cobra traslado. Si cambia de localidad cambia el número de teléfono. | F11: Presencial | G11: Tendencia: la energía queda al propietario y el inquilino traslada TIC | H11: IO 02.03 §5.2.7
A12: T11 | B12: Facturación de obras TIC | C12: La pide IPTV por mail. | D12: Igual que E12. | E12: Igual que E12. | F12: Mail interno | G12: IPTV; Contaduría | H12: IO 02.03 §5.2.8

Sheet Movilcoop
A1: ID | B1: Gestión | C1: Quién puede pedirla / condiciones | D1: Documentación | E1: Costo / qué se cobra | F1: Canales | G1: Intervienen / a quién se deriva | H1: Fuente | I1: Validación Ventas | J1: Validación Call Center | K1: Validación Mesa de Informes | L1: Observaciones / info nueva
A2: M01 | B2: Alta de línea | C2: Titular de la luz con 6 meses de antigüedad, al día. Si dio de baja una línea, no puede sacar otra por 1 año. | D2: DNI (copia); contrato y recibo. | E2: Plan Ilimitado 4 GB. Equipo financiado en la cuenta de energía. | F2: Presencial / Agentes externos | G2: Depósito (factura el equipo) | H2: PG 02 §5.6.1
A3: M02 | B3: Baja de línea | C3: Mínimo 1 año desde el alta; sin deuda. Pierde el número. | D3: — | E3: Quedan 1 o 2 facturas por llegar. | F3: Presencial | G3: Se reciben del 1 al 15; se envían a Claro antes del 19 | H3: PG 02 §5.6.3
A4: M03 | B4: Reconexión | C4: Solo líneas suspendidas por falta de pago (no dadas de baja ni canceladas por Claro). | D4: — | E4: Se cobra reconexión. | F4: Presencial | G4: Se reconecta al final del día por autogestión Claro | H4: PG 02 §5.6.5
A5: M04 | B5: Transferencia | C5: Vienen ambas partes con DNI; el nuevo titular debe tener energía a su nombre. | D5: DNI de ambos. | E5: Sin costo. | F5: Presencial | H5: PG 02 §5.6.6
A6: M05 | B6: Cambio de plan | C6: Se pide por reclamo. | D6: Línea, plan actual y plan deseado. | E6: — | F6: Reclamo | G6: Claro | H6: PG 02 §5.6.9
A7: M06 | B7: Desbloqueo de equipo negado | C7: Deuda saldada. | D7: IMEI, número de línea, foto del DNI del responsable. | E7: Se factura un abono (costo de reactivación). | F7: Presencial | G7: Claro | H7: PG 02 §5.6.8
A8: M07 | B8: Pase de titularidad de la Cooperativa a Claro | C8: 1 año de antigüedad y cuentas al día. | D8: DNI; formularios SDS-cambio-TT, ACP-Masivo y SDS-11 si es más de una línea. | E8: — | F8: Presencial | G8: Claro | H8: PG 02 §5.6.10
A9: M08 | B9: Pedidos por autogestión Claro | C9: — | D9: — | E9: — | F9: Interno | G9: Equipos, SIM/eSIM, seguimiento y activación | H9: PG 02 §5.6.7

Sheet Otros servicios
A1: ID | B1: Gestión | C1: Quién puede pedirla / condiciones | D1: Documentación | E1: Costo / qué se cobra | F1: Canales | G1: Intervienen / a quién se deriva | H1: Fuente | I1: Validación Ventas | J1: Validación Call Center | K1: Validación Mesa de Informes | L1: Observaciones / info nueva
A2: O01 | B2: Pago directo – alta | C2: Titular de la cuenta bancaria. | D2: Planilla: datos del titular, banco, CBU/alias, cuentas a adherir. | E2: — | F2: Presencial / Web | H2: PG 02 §5.4.1
A3: O02 | B3: Pago directo – baja | C3: Titular. | D3: Planilla. | E3: — | F3: Presencial / Web | H3: PG 02 §5.4.2
A4: O03 | B4: APROSS – afiliaciones nuevas | C4: SUSPENDIDAS por resolución de APROSS. | D4: — | E4: — | F4: — | G4: APROSS | H4: PG 02 §5.5
A5: O04 | B5: APROSS – continuidad por pérdida de empleo / recién nacido | C5: Afiliado existente. | D5: Planillas APROSS (DJ de salud, ficha afiliatoria, agregar/renovar familiares, etc.). | E5: — | F5: Presencial | G5: APROSS (entidadesvoluntarias@apross.gov.ar) | H5: PG 02 §5.5
A6: O05 | B6: APROSS – bajas | C6: Voluntaria, por fallecimiento o por deuda. | D6: Ficha de baja. | E6: — | F6: Presencial | G6: APROSS | H6: PG 02 §5.5
A7: O06 | B7: APROSS – control de deuda | C7: — | D7: — | E7: Intimación por mail; el día 10 de cada mes se informa la baja por deuda. | F7: Interno | G7: APROSS | H7: PG 02 §5.5
A8: O07 | B8: Seguro de vida / subsidio por fallecimiento (Red Bienestar) | C8: Socio con energía o agua activa. | D8: DNI de 2 beneficiarios; planilla firmada. | E8: — | F8: Presencial | H8: PG 02 Servicios sociales / Anexo IV
A9: O08 | B9: Servicio de sepelio | C9: Socio con energía o agua activa. | D9: Libreta de familia o DNI del grupo familiar; planilla firmada. | E9: Se cobra inscripción. | F9: Presencial | H9: PG 02 §5.7.2 / Anexo III
A10: O09 | B10: Banco de Sangre | C10: Socio con energía o agua activa. | D10: Libreta de familia o DNI del grupo familiar. | E10: — | F10: Presencial | G10: A CONFIRMAR si lo hace Ventas o el Banco de Sangre | H10: PG 02 §5.7.3
A11: O10 | B11: Baja de servicios sociales | C11: La pide el titular. | D11: Planilla de baja por cada servicio. | E11: — | F11: Presencial | H11: PG 02 Servicios sociales

Sheet General y administrativo
A1: ID | B1: Gestión | C1: Quién puede pedirla / condiciones | D1: Documentación | E1: Costo / qué se cobra | F1: Canales | G1: Intervienen / a quién se deriva | H1: Fuente | I1: Validación Ventas | J1: Validación Call Center | K1: Validación Mesa de Informes | L1: Observaciones / info nueva
A2: G01 | B2: Atención de consultas y trámites | C2: Socio o no socio (define requisitos). | D2: Presencial: se entrega Anexo I de requisitos. Web: si falta algo se avisa por mail o teléfono. | E2: — | F2: Presencial / Web / Teléfono | H2: PG 02 §5
A3: G02 | B3: Casillas de mail | C3: — | D3: trámites@ (trámites web y autorizaciones), reclamos@, jefes@, mails personales. | E3: Consultas particulares o pedidos de trámites no se responden por mail. | F3: Mail | H3: PG 02 Correos
A4: G03 | B4: Control de deuda y financiación | C4: — | D4: Aviso a deudor y garante (mail o papel). | E4: A las 48 h: financiar, corte puntual o Veraz. Cuotas según importe, con tasa de interés. | F4: Interno | G4: Facturación; Gerencia Administrativa | H4: PG 02 §5.10
A5: G04 | B5: Facturación de cuotas de convenios de obras | C5: A CONFIRMAR: el PG dice que ya no lo hace Atención al Cliente. | D5: — | E5: Primeros días de cada mes. | F5: Interno | G5: Contaduría | H5: PG 02 §5.5 / IO 02.02 / IO 02.03
A6: G05 | B6: Padrones y distritos para asambleas | C6: Distrito de votación = distrito del servicio activo. | D6: — | E6: Control al 30/6. 1 delegado cada 200 asociados. Votan socios con 6 meses de antigüedad. 3 copias padrón general + 3 habilitados. | F6: Interno | G6: Sistemas; Secretaría (envía a Subsecretaría de Cooperativas e INAES) | H6: PG 02 §5.8
A7: G06 | B7: Libros de capitales | C7: Por servicio (energía, agua, teléfono) al 30/6. | D7: Hojas foliadas selladas por juez de paz. | E7: Se imprimen en julio. | F7: Interno | H7: PG 02 §5.9

Sheet Criterios comunes
A1: Tema | B1: Energía | C1: Agua | D1: TIC | E1: Movilcoop | F1: Servicios sociales | G1: Criterio único propuesto | H1: Validación Ventas | I1: Validación Call Center | J1: Validación Mesa de Informes
A2: Garante | B2: Socio de la Cooperativa y propietario (según figuras; el texto solo dice socio). | C2: A confirmar si aplica (servicio a nombre del propietario). | D2: Teléfono/internet: cualquier asociado titular de energía. Inalámbrico: garante o 2 meses de abono adelantado. | E2: No aplica. | F2: No aplica.
A3: Depósito en garantía | B3: Si no hay garante: 4 cuotas, la 1ª de contado. Se devuelve en la baja. | C3: A confirmar. | D3: Mencionado, sin monto ni forma de pago. | E3: No aplica. | F3: No aplica.
A4: ¿Hay que ser socio? | B4: No. | C4: Propietario. | D4: Fibra: sí o conectar teléfono antes. TV: sí + internet. Inalámbrico: no. | E4: Titular de la luz con 6 meses. | F4: Energía o agua activa.
A5: Reconexión con corte > 30 días | B5: Titular o autorización del titular. Si retiraron medidor: certificado apto + inspección. | C5: Sin desarrollar. | D5: Titular o autorización del titular. | E5: Solo suspendidas por falta de pago. | F5: —
A6: Canales de reconexión | B6: Presencial; pedidos de caja por WhatsApp. | C6: Presencial / Web. | D6: Presencial / Web / Caja automática. | E6: Presencial. | F6: —
A7: Baja | B7: Titular. Toma de lectura previa y reintegro de depósito. | C7: Titular + DJ vivienda libre de ocupantes. | D7: Titular + devolución de equipos en comodato. | E7: 1 año mínimo; sin deuda; del 1 al 15. | F7: Titular, planilla por servicio.
A8: Cambio de titularidad | B8: Inquilinos, inquilino↔propietario, fallecimiento. Ambas partes. | C8: Solo fallecimiento o compra. | D8: Cambio de inquilino, fallecimiento o necesidad. | E8: Transferencia: ambas partes, nuevo titular con energía. Sin costo. | F8: —
A9: Traslado | B9: Sin deuda, disponibilidad técnica; inquilino: contrato + renovar garantía; propietario: escritura. | C9: No existe. | D9: Igual que energía. Cambio de localidad = nuevo número. | E9: — | F9: —
A10: Quién factura / cobra | B10: Ventas factura el trámite. | C10: Ventas factura el trámite. | D10: Ventas; reconexión automática en caja. | E10: Equipos: Depósito. | F10: Sepelio: inscripción por ventas varias.

Sheet Pendientes y contradicciones
A1: N° | B1: Servicio | C1: Tipo | D1: Tema | E1: Detalle | F1: Fuente | G1: Quién define | H1: Estado | I1: Resolución
A2: 1 | B2: Energía | C2: Sin desarrollar | D2: Financiaciones | E2: Punto 5.1.7 vacío ('falta desarrollar algo Patri'). | F2: IO 02.01 §5.1.7 | H2: Abierto
A3: 2 | B3: Energía | C3: Sin desarrollar | D3: Prórrogas | E3: Punto 5.1.8 vacío. | F3: IO 02.01 §5.1.8 | H3: Abierto
A4: 3 | B4: Energía | C4: Sin desarrollar | D4: Certificado conexión nueva vs existente | E4: Dice 'se diferencia por xxxx (desarrolla Patri)'. | F4: IO 02.01 §5.1.1 | H4: Abierto
A5: 4 | B5: Energía | C5: Contradicción | D5: Requisitos del garante | E5: Texto: socio. Figuras: socio y propietario. | F5: IO 02.01 §5.1.1 / Fig. 1-2 | H5: Abierto
A6: 5 | B6: Energía | C6: Contradicción | D6: Vigencia del certificado apto | E6: En un punto 4 casos (5/3/2/1 años), en otro solo vivienda 5 y comercio 3. | F6: IO 02.01 §5.1.1 | H6: Abierto
A7: 6 | B7: Energía | C7: Contradicción | D7: Figuras de requisitos | E7: Monofásica propietario sin foto firmada (trifásica sí); 'Escritura copia' en trifásica inquilino; numeración repetida; no queda claro si ARCA/IIBB es solo comercio. | F7: IO 02.01 Fig. 1-2 | H7: Abierto
A8: 7 | B8: Energía | C8: A confirmar | D8: Tarifas y opciones del sistema | E8: Hay opciones que ya no se usan (quedó para ver con Ricardo). | F8: IO 02.01 §5.1.1 | H8: Abierto
A9: 8 | B9: Energía | C9: A confirmar | D9: Pilares hasta 5 kVA | E9: Quedó para ver con Juan o Gino; el texto dice '5 WK'. | F9: IO 02.01 §5.1.1 | H9: Abierto
A10: 9 | B10: Energía | C10: A confirmar | D10: Canal WhatsApp 'Teletrabajo' | E10: El texto dice 'se trataba': ¿sigue vigente para reconexiones y quita de cepo? | F10: IO 02.01 §5.1.2 | H10: Abierto
A11: 10 | B11: Energía | C11: A confirmar | D11: Certificado en traslados | E11: En el traslado no se menciona el certificado apto. | F11: IO 02.01 §5.1.5 | H11: Abierto
A12: 11 | B12: Energía | C12: Error de forma | D12: Anexos y registros | E12: Legislación como Anexo X y IX; faltan anexos IV y V; RPG 02.01 vs RIO 02.01; mail 'tramites*coop5'. | F12: IO 02.01 | H12: Abierto
A13: 12 | B13: Agua | C13: Contradicción | D13: Inquilinos y garante | E13: Pide garante si es inquilino, pero el servicio va siempre a nombre del propietario; la figura solo tiene columna propietario. | F13: IO 02.02 §5.2 / §5.2.5 | H13: Abierto
... A24: 23 | B24: General | C24: Mejora | D24: Nombres propios | E24: Reemplazar nombres (Franco, Patricia, Martín, Agustina, Mauricio, Ricardo, Juan) por puesto o sector. | F24: Todos | H24: Abierto
